hardline/__init__.py
hardline/androidtools.py
hardline/cachingproxy.py
hardline/cidict.py
hardline/daemonconfig.py
hardline/directories.py
hardline/drayerdb.py
hardline/hardline.py
hardline/keystore.py
hardline/kouchat.py
hardline/libnacl.py
hardline/selfsigned.py
hardline/upnpwrapper.py
hardline/ws4py_drayer.py
hardline/gui/__init__.py
hardline/gui/barcodes.py
hardline/gui/colornames.py
hardline/gui/discovery.py
hardline/gui/kivymdfmfork.py
hardline/gui/posts.py
hardline/gui/servicesUI.py
hardline/gui/streams.py
hardline/gui/tables.py
hardline/gui/tools.py
hardline/gui/uihelpers.py
hardline/simpleeval/__init__.py
hardline/upnpclient/__init__.py
hardline/upnpclient/const.py
hardline/upnpclient/errors.py
hardline/upnpclient/marshal.py
hardline/upnpclient/soap.py
hardline/upnpclient/ssdp.py
hardline/upnpclient/upnp.py
hardline/upnpclient/util.py
hardline/util/__init__.py
hardline/websockets/__init__.py
hardline/websockets/__main__.py
hardline/websockets/client.py
hardline/websockets/connection.py
hardline/websockets/datastructures.py
hardline/websockets/exceptions.py
hardline/websockets/frames.py
hardline/websockets/headers.py
hardline/websockets/http.py
hardline/websockets/http11.py
hardline/websockets/imports.py
hardline/websockets/server.py
hardline/websockets/streams.py
hardline/websockets/typing.py
hardline/websockets/uri.py
hardline/websockets/utils.py
hardline/websockets/version.py
hardline/websockets/extensions/__init__.py
hardline/websockets/extensions/base.py
hardline/websockets/extensions/permessage_deflate.py
hardline/websockets/legacy/__init__.py
hardline/websockets/legacy/auth.py
hardline/websockets/legacy/client.py
hardline/websockets/legacy/framing.py
hardline/websockets/legacy/handshake.py
hardline/websockets/legacy/http.py
hardline/websockets/legacy/protocol.py
hardline/websockets/legacy/server.py
hardline-0.21.1.data/scripts/hardline-gui
hardline-0.21.1.data/scripts/hardlined
service/__init__.py
service/main.py
hardline-0.21.1.dist-info/LICENSE
hardline-0.21.1.dist-info/METADATA
hardline-0.21.1.dist-info/WHEEL
hardline-0.21.1.dist-info/top_level.txt
hardline-0.21.1.dist-info/RECORD
