Metadata-Version: 2.1
Name: hardline
Version: 0.21.1
Summary: HardlineP2P is a way to make web services securely acessible to the world, without any manual DNS or certificate setup
Home-page: https://github.com/EternityForest/hardlinep2p
Author: Daniel Dunn
Author-email: dannydunn@eternityforest.com
License: UNKNOWN
Platform: UNKNOWN
Classifier: Programming Language :: Python :: 3
Classifier: License :: OSI Approved :: GNU General Public License v3 (GPLv3)
Classifier: Operating System :: OS Independent
Requires-Python: >=3.6
Requires-Dist: pynacl
Requires-Dist: requests
Requires-Dist: lxml
Requires-Dist: six
Requires-Dist: python-dateutil
Requires-Dist: kivy
Requires-Dist: kivymd
Requires-Dist: mako
Requires-Dist: cryptography
Requires-Dist: netifaces
Requires-Dist: beautifulsoup4
Requires-Dist: qrcode
Requires-Dist: pillow
Requires-Dist: plyer
Requires-Dist: pint
Requires-Dist: kivy-garden.qrcode
Requires-Dist: colorzero
Requires-Dist: wikipedia
Requires-Dist: pygments
